bread_messenger_server-0.1.data/scripts/server_run
server/__init__.py
server/server_main.py
server/common/__init__.py
server/common/decorators.py
server/common/descriptors.py
server/common/errors.py
server/common/metaclasses.py
server/common/utils.py
server/common/variables.py
server/logs/__init__.py
server/logs/config_server_log.py
server/server/__init__.py
server/server/add_user.py
server/server/config_window.py
server/server/core.py
server/server/del_user.py
server/server/main_window.py
server/server/server_database.py
server/server/stat_window.py
server/unit_test/__init__.py
bread_messenger_server-0.1.dist-info/METADATA
bread_messenger_server-0.1.dist-info/WHEEL
bread_messenger_server-0.1.dist-info/top_level.txt
bread_messenger_server-0.1.dist-info/RECORD
