Metadata-Version: 2.1
Name: bread-messenger-server
Version: 0.1
Summary: This is my study project. Fresh, raw and uncooked like a loaf of bread made for the first time. Server.
Home-page: UNKNOWN
Author: LtBread
Author-email: primebox21@gmail.com
License: UNKNOWN
Platform: UNKNOWN
Requires-Dist: PyQt5
Requires-Dist: sqlalchemy
Requires-Dist: pycryptodome
Requires-Dist: pycryptodomex
